<?xml version="1.0" encoding="UTF-8" standalone="no"?>
<annotation>
    <folder>C:\Users\marku\Desktop\whale_data\images</folder>
    <filename>0679f42ec.jpg</filename>
    <size>
        <width>1050</width>
        <height>700</height>
        <depth>3</depth>
    </size>
    <object>
        <name>Fluke</name>
        <difficult>0</difficult>
        <occluded>0</occluded>
        <pose>Unspecified</pose>
        <truncated>0</truncated>
        <bndbox>
            <xmin>56.16</xmin>
            <xmax>1014.4</xmax>
            <ymin>43.62</ymin>
            <ymax>531.52</ymax>
        </bndbox>
    </object>
</annotation>
