<?xml version="1.0" encoding="UTF-8" standalone="no"?>
<annotation>
    <folder>C:\Users\marku\Desktop\whale_data\images</folder>
    <filename>a3280586a.jpg</filename>
    <size>
        <width>1050</width>
        <height>700</height>
        <depth>3</depth>
    </size>
    <object>
        <name>Fluke</name>
        <difficult>0</difficult>
        <occluded>0</occluded>
        <pose>Unspecified</pose>
        <truncated>0</truncated>
        <bndbox>
            <xmin>76.27</xmin>
            <xmax>915.23</xmax>
            <ymin>121.44</ymin>
            <ymax>487.98</ymax>
        </bndbox>
    </object>
</annotation>
