<?xml version="1.0" encoding="UTF-8" standalone="no"?>
<annotation>
    <folder>C:\Users\marku\Desktop\whale_data\images</folder>
    <filename>c9f3a52b9.jpg</filename>
    <size>
        <width>1048</width>
        <height>701</height>
        <depth>3</depth>
    </size>
    <object>
        <name>Fluke</name>
        <difficult>0</difficult>
        <occluded>0</occluded>
        <pose>Unspecified</pose>
        <truncated>0</truncated>
        <bndbox>
            <xmin>249.96</xmin>
            <xmax>745.3</xmax>
            <ymin>184.99</ymin>
            <ymax>517.5</ymax>
        </bndbox>
    </object>
</annotation>
